kaldi_python_io/__init__.py
kaldi_python_io/_io_kernel.py
kaldi_python_io/functional.py
kaldi_python_io/inst.py
kaldi_python_io-1.0.1.dist-info/LICENSE
kaldi_python_io-1.0.1.dist-info/METADATA
kaldi_python_io-1.0.1.dist-info/WHEEL
kaldi_python_io-1.0.1.dist-info/top_level.txt
kaldi_python_io-1.0.1.dist-info/RECORD
